mars_gym/__init__.py
mars_gym/cli.py
mars_gym/config.py
mars_gym/cuda.py
mars_gym/luigi.cfg
mars_gym/meta_config.py
mars_gym/data/__init__.py
mars_gym/data/dataset.py
mars_gym/data/task.py
mars_gym/data/utils.py
mars_gym/evaluation/__init__.py
mars_gym/evaluation/policy_estimator.py
mars_gym/evaluation/propensity_score.py
mars_gym/evaluation/task.py
mars_gym/evaluation/metrics/__init__.py
mars_gym/evaluation/metrics/fairness.py
mars_gym/evaluation/metrics/offpolicy.py
mars_gym/evaluation/metrics/rank.py
mars_gym/gym/__init__.py
mars_gym/gym/envs/__init__.py
mars_gym/gym/envs/recsys.py
mars_gym/model/__init__.py
mars_gym/model/abstract.py
mars_gym/model/agent.py
mars_gym/model/bandit.py
mars_gym/model/base_model.py
mars_gym/model/policy_estimator.py
mars_gym/simulation/__init__.py
mars_gym/simulation/interaction.py
mars_gym/simulation/training.py
mars_gym/tools/__init__.py
mars_gym/tools/eval_viz/__init__.py
mars_gym/tools/eval_viz/app.py
mars_gym/tools/eval_viz/plot.py
mars_gym/tools/eval_viz/util.py
mars_gym/tools/eval_viz/pages/__init__.py
mars_gym/tools/eval_viz/pages/home.py
mars_gym/tools/eval_viz/pages/model.py
mars_gym/torch/__init__.py
mars_gym/torch/data.py
mars_gym/torch/init.py
mars_gym/torch/loss.py
mars_gym/torch/metrics.py
mars_gym/torch/optimizer.py
mars_gym/torch/summary.py
mars_gym/utils/__init__.py
mars_gym/utils/files.py
mars_gym/utils/index_mapping.py
mars_gym/utils/plot.py
mars_gym/utils/reflection.py
mars_gym/utils/utils.py
mars_gym-0.1.0.dist-info/AUTHORS.rst
mars_gym-0.1.0.dist-info/LICENSE
mars_gym-0.1.0.dist-info/METADATA
mars_gym-0.1.0.dist-info/WHEEL
mars_gym-0.1.0.dist-info/entry_points.txt
mars_gym-0.1.0.dist-info/top_level.txt
mars_gym-0.1.0.dist-info/RECORD
