Metadata-Version: 2.1
Name: mars-gym
Version: 0.1.0
Summary: Framework Code for the RecSys 2020 entitled 'MARS-Gym: A Gym framework to model, train, and evaluate recommendationsystems for marketplaces'.
Home-page: https://github.com/deeplearningbrasil/mars-gym
Author: MARS-Gym Authors
Author-email: mars-gym@googlegroups.com
License: MIT
Project-URL: Documentation, https://mars-gym.readthedocs.io/
Project-URL: Changelog, https://mars-gym.readthedocs.io/en/latest/changelog.html
Project-URL: Issue Tracker, https://github.com/deeplearningbrasil/mars-gym/issues
Platform: UNKNOWN
Classifier: Development Status :: 5 - Production/Stable
Classifier: Intended Audience :: Developers
Classifier: Intended Audience :: Science/Research
Classifier: License :: OSI Approved :: MIT License
Classifier: Operating System :: OS Independent
Classifier: Programming Language :: Python
Classifier: Programming Language :: Python :: 3
Classifier: Programming Language :: Python :: 3.6
Classifier: Programming Language :: Python :: 3.7
Classifier: Programming Language :: Python :: 3.8
Classifier: Programming Language :: Python :: Implementation :: CPython
Classifier: Programming Language :: Python :: Implementation :: PyPy
Classifier: Topic :: Scientific/Engineering :: Artificial Intelligence
Requires-Python: >=3.6
Requires-Dist: luigi (<3.0,>=2.8)
Requires-Dist: gym (<1,>=0.15)
Requires-Dist: numpy (<2,>=1.17)
Requires-Dist: scipy (<2,>=1.3)
Requires-Dist: pandas (<1,>=0.25)
Requires-Dist: pyspark (<3,>=2.4)
Requires-Dist: matplotlib (<3,>=2.2)
Requires-Dist: seaborn (<1,>=0.8)
Requires-Dist: plotly (<5,>=4.4)
Requires-Dist: streamlit (==0.62)
Requires-Dist: torch (==1.2)
Requires-Dist: torchbearer (==0.5)
Requires-Dist: pytorch-nlp (>=0.4)
Requires-Dist: scikit-learn (<1,>=0.21)
Requires-Dist: imbalanced-learn (<1,>=0.4)
Requires-Dist: tensorboardx (<2,>=1.6)
Requires-Dist: tqdm (<5)
Requires-Dist: requests (<3,>=2)
Requires-Dist: diskcache (<4,>=3)
Requires-Dist: psutil (<6,>=5)
Requires-Dist: click (>=7.0)
Requires-Dist: docutils (==0.15)
